iplocate/__init__.py
iplocate/client.py
iplocate/exceptions.py
iplocate/models.py
python_iplocate-1.0.0.dist-info/licenses/LICENSE
python_iplocate-1.0.0.dist-info/METADATA
python_iplocate-1.0.0.dist-info/WHEEL
python_iplocate-1.0.0.dist-info/top_level.txt
python_iplocate-1.0.0.dist-info/RECORD
